melnor_bluetooth/__init__.py
melnor_bluetooth/constants.py
melnor_bluetooth/device.py
melnor_bluetooth/models/frequency.py
melnor_bluetooth/scanner.py
melnor_bluetooth/utils/battery.py
melnor_bluetooth/utils/date.py
melnor_bluetooth/utils/formatter.py
melnor_bluetooth/utils/lock.py
melnor_bluetooth-0.0.24.dist-info/LICENSE
melnor_bluetooth-0.0.24.dist-info/METADATA
melnor_bluetooth-0.0.24.dist-info/WHEEL
melnor_bluetooth-0.0.24.dist-info/RECORD
