Metadata-Version: 2.1
Name: melnor-bluetooth
Version: 0.0.24
Summary: A small python library for discovery and interacting with Melnor, Eden, etc Bluetooth water timers.
License: MIT
Keywords: bluetooth,melnor,home automation,irrigation,gardening
Author: Justin Vanderhooft
Author-email: justinvdhooft@gmail.com
Requires-Python: >=3.9,<4.0
Classifier: Development Status :: 3 - Alpha
Classifier: Intended Audience :: Developers
Classifier: License :: OSI Approved :: MIT License
Classifier: Programming Language :: Python :: 3
Classifier: Programming Language :: Python :: 3.9
Classifier: Programming Language :: Python :: 3.10
Classifier: Programming Language :: Python :: 3.11
Classifier: Topic :: Home Automation
Classifier: Topic :: Software Development :: Libraries :: Python Modules
Requires-Dist: Deprecated (>=1.2.13)
Requires-Dist: aioconsole (>=0.4.1)
Requires-Dist: bleak (>=0.15.1)
Requires-Dist: bleak-retry-connector (>=1.11.0)
Requires-Dist: tzdata (>=2022.1)
Requires-Dist: tzlocal (>=4.1)
